dlock13-open
setup.py
dlock13/__init__.py
dlock13/dlock.py
dlock13.egg-info/PKG-INFO
dlock13.egg-info/SOURCES.txt
dlock13.egg-info/dependency_links.txt
dlock13.egg-info/requires.txt
dlock13.egg-info/top_level.txt
test/test_doorlock.py
test/test_doorlock_flask.py