Metadata-Version: 1.1
Name: dlock13
Version: 0.4.1
Summary: Python API for MQTT-based doorlocks
Home-page: https://github.com/bitraf/dlock13
Author: Jon Nordby
Author-email: jononor@gmail.com
License: MIT License
Platform: UNKNOWN
Classifier: Environment :: Web Environment
Classifier: Intended Audience :: Developers
Classifier: License :: OSI Approved :: MIT License
Classifier: Operating System :: OS Independent
Classifier: Programming Language :: Python
Classifier: Programming Language :: Python :: 2
Classifier: Programming Language :: Python :: 2.7
Classifier: Programming Language :: Python :: 2.6
Classifier: Topic :: Internet :: WWW/HTTP
